nqxpack/__init__.py
nqxpack/registry.py
nqxpack/_src/__init__.py
nqxpack/_src/api.py
nqxpack/_src/contextmgr.py
nqxpack/_src/distributed.py
nqxpack/_src/errors.py
nqxpack/_src/io.py
nqxpack/_src/lib_v1/__init__.py
nqxpack/_src/lib_v1/asset_lib.py
nqxpack/_src/lib_v1/closure.py
nqxpack/_src/lib_v1/custom_types.py
nqxpack/_src/lib_v1/lib.py
nqxpack/_src/lib_v1/resolution.py
nqxpack/_src/lib_v1/versioninfo.py
nqxpack/_src/metadata/generate_metadata.py
nqxpack/_src/registry/__init__.py
nqxpack/_src/registry/flax.py
nqxpack/_src/registry/hydra.py
nqxpack/_src/registry/jax.py
nqxpack/_src/registry/netket.py
nqxpack/_src/registry/netket_operator.py
nqxpack/_src/registry/stdlib.py
nqxpack/_src/registry/versioninfo.py
nqxpack-0.1.2.dist-info/METADATA
nqxpack-0.1.2.dist-info/WHEEL
nqxpack-0.1.2.dist-info/entry_points.txt
nqxpack-0.1.2.dist-info/RECORD
