Metadata-Version: 2.4
Name: nqxpack
Version: 0.1.2
Summary: Library to serialise objects arising from scientific and Machine Learning libraries, including NetKet.
Author-email: Filippo Vicentini <filippovicentini@gmail.com>
Requires-Python: >=3.10
Requires-Dist: flax>=0.10.2
Requires-Dist: jax>=0.4.35
Requires-Dist: netket>=3.16.0.post2
Requires-Dist: numpy>=2
Requires-Dist: omegaconf>=2
